muse_origin/Dico_3FWHM.fits
muse_origin/Dico_FWHM_2_12.fits
muse_origin/__init__.py
muse_origin/lib_origin.py
muse_origin/origin.py
muse_origin/source_creation.py
muse_origin/source_masks.py
muse_origin/source_update.py
muse_origin/steps.py
muse_origin/version.py
tests/__init__.py
tests/test_origin.py
muse_origin-3.2.dist-info/LICENSE
muse_origin-3.2.dist-info/METADATA
muse_origin-3.2.dist-info/WHEEL
muse_origin-3.2.dist-info/top_level.txt
muse_origin-3.2.dist-info/RECORD
