Metadata-Version: 2.1
Name: muse-origin
Version: 3.2
Summary: Blind detection of faint emission line galaxies in MUSE datacubes
Home-page: https://github.com/musevlt/origin
Author: Simon Conseil
Author-email: simon.conseil@univ-lyon1.fr
License: MIT License
Keywords: astronomy,astrophysics,science,muse,vlt
Platform: UNKNOWN
Classifier: Intended Audience :: Science/Research
Classifier: License :: OSI Approved :: MIT License
Classifier: Operating System :: OS Independent
Classifier: Programming Language :: Python :: 3
Classifier: Programming Language :: Python :: 3.6
Classifier: Programming Language :: Python :: 3.7
Classifier: Programming Language :: Python :: Implementation :: CPython
Classifier: Topic :: Scientific/Engineering :: Astronomy
Classifier: Topic :: Scientific/Engineering :: Physics
Requires-Python: >=3.6
Requires-Dist: numpy
Requires-Dist: scipy
Requires-Dist: matplotlib
Requires-Dist: astropy
Requires-Dist: mpdaf
Requires-Dist: tqdm
Requires-Dist: joblib
Requires-Dist: PyYAML
Requires-Dist: photutils (>=0.5)
Provides-Extra: docs
Requires-Dist: numpydoc (>=0.9) ; extra == 'docs'
Requires-Dist: sphinx-rtd-theme ; extra == 'docs'
Requires-Dist: sphinx-automodapi ; extra == 'docs'
Requires-Dist: nbsphinx ; extra == 'docs'
